seizurekit/__init__.py
seizurekit/eval_epochs.py
seizurekit/eval_events.py
seizurekit/eval_utils.py
seizurekit/stats/__init__.py
seizurekit/stats/stat.py
seizurekit/viz/__init__.py
seizurekit/viz/toy_example.py
seizurekit-0.1.1.dist-info/METADATA
seizurekit-0.1.1.dist-info/WHEEL
seizurekit-0.1.1.dist-info/entry_points.txt
seizurekit-0.1.1.dist-info/top_level.txt
seizurekit-0.1.1.dist-info/RECORD
